authenticated_signals/__init__.py
authenticated_signals/__version__.py
authenticated_signals/apps.py
authenticated_signals/middleware.py
authenticated_signals/models.py
authenticated_signals/signals.py
django_authenticated_signals-0.0.2b1.dist-info/LICENSE
django_authenticated_signals-0.0.2b1.dist-info/METADATA
django_authenticated_signals-0.0.2b1.dist-info/WHEEL
django_authenticated_signals-0.0.2b1.dist-info/top_level.txt
django_authenticated_signals-0.0.2b1.dist-info/RECORD
