Metadata-Version: 2.1
Name: django-authenticated-signals
Version: 0.0.2b1
Summary: The Django-Authenticated-Signals package provides signals with additional `request` parameter
Home-page: https://github.com/nnseva/django-authenticated-signals
Author: Vsevolod Novikov
Author-email: nnseva@gmail.com
License: LGPL
Keywords: django signal authenticated request user
Platform: any
Classifier: Development Status :: 4 - Beta
Classifier: Intended Audience :: Developers
Classifier: Topic :: Software Development :: Libraries
Classifier: Environment :: Web Environment
Classifier: Framework :: Django
Classifier: Framework :: Django :: 1.10
Classifier: Framework :: Django :: 1.11
Classifier: License :: OSI Approved :: GNU Library or Lesser General Public License (LGPL)
Classifier: Programming Language :: Python :: 2
Classifier: Programming Language :: Python :: 2.7
Classifier: Programming Language :: Python :: 3
Classifier: Programming Language :: Python :: 3.4
Classifier: Programming Language :: Python :: 3.5
License-File: LICENSE
Requires-Dist: django
